YouxiYinqingKaifaRumenjiaochengCYuyanBianchengWangFix1/README.md
YouxiYinqingKaifaRumenjiaochengCYuyanBianchengWangFix1/__init__.py
YouxiYinqingKaifaRumenjiaochengCYuyanBianchengWangFix1/__main__.py
YouxiYinqingKaifaRumenjiaochengCYuyanBianchengWangFix1/file.epub
YouxiYinqingKaifaRumenjiaochengCYuyanBianchengWangFix1/index.html
YouxiYinqingKaifaRumenjiaochengCYuyanBianchengWangFix1/css/__init__.py
YouxiYinqingKaifaRumenjiaochengCYuyanBianchengWangFix1/css/annotations.css
YouxiYinqingKaifaRumenjiaochengCYuyanBianchengWangFix1/css/main.css
YouxiYinqingKaifaRumenjiaochengCYuyanBianchengWangFix1/css/normalize.css
YouxiYinqingKaifaRumenjiaochengCYuyanBianchengWangFix1/css/popup.css
YouxiYinqingKaifaRumenjiaochengCYuyanBianchengWangFix1/font/__init__.py
YouxiYinqingKaifaRumenjiaochengCYuyanBianchengWangFix1/font/fontello.eot
YouxiYinqingKaifaRumenjiaochengCYuyanBianchengWangFix1/font/fontello.svg
YouxiYinqingKaifaRumenjiaochengCYuyanBianchengWangFix1/font/fontello.ttf
YouxiYinqingKaifaRumenjiaochengCYuyanBianchengWangFix1/font/fontello.woff
YouxiYinqingKaifaRumenjiaochengCYuyanBianchengWangFix1/img/__init__.py
YouxiYinqingKaifaRumenjiaochengCYuyanBianchengWangFix1/img/annotator-glyph-sprite.png
YouxiYinqingKaifaRumenjiaochengCYuyanBianchengWangFix1/img/annotator-icon-sprite.png
YouxiYinqingKaifaRumenjiaochengCYuyanBianchengWangFix1/img/apple-touch-icon.png
YouxiYinqingKaifaRumenjiaochengCYuyanBianchengWangFix1/img/cancelfullscreen.png
YouxiYinqingKaifaRumenjiaochengCYuyanBianchengWangFix1/img/close.png
YouxiYinqingKaifaRumenjiaochengCYuyanBianchengWangFix1/img/fullscreen.png
YouxiYinqingKaifaRumenjiaochengCYuyanBianchengWangFix1/img/loader.gif
YouxiYinqingKaifaRumenjiaochengCYuyanBianchengWangFix1/img/menu-icon.png
YouxiYinqingKaifaRumenjiaochengCYuyanBianchengWangFix1/img/save.png
YouxiYinqingKaifaRumenjiaochengCYuyanBianchengWangFix1/img/saved.png
YouxiYinqingKaifaRumenjiaochengCYuyanBianchengWangFix1/img/settings-s.png
youxi_yinqing_kaifa_rumenjiaocheng_c_yuyan_biancheng_wang_fix1-2025.3.24.1.dist-info/METADATA
youxi_yinqing_kaifa_rumenjiaocheng_c_yuyan_biancheng_wang_fix1-2025.3.24.1.dist-info/WHEEL
youxi_yinqing_kaifa_rumenjiaocheng_c_yuyan_biancheng_wang_fix1-2025.3.24.1.dist-info/entry_points.txt
youxi_yinqing_kaifa_rumenjiaocheng_c_yuyan_biancheng_wang_fix1-2025.3.24.1.dist-info/top_level.txt
youxi_yinqing_kaifa_rumenjiaocheng_c_yuyan_biancheng_wang_fix1-2025.3.24.1.dist-info/RECORD
